powerfit/__init__.py
powerfit/_version.py
powerfit-0.3.1.dist-info/LICENSE
powerfit-0.3.1.dist-info/METADATA
powerfit-0.3.1.dist-info/WHEEL
powerfit-0.3.1.dist-info/top_level.txt
powerfit-0.3.1.dist-info/RECORD
