Metadata-Version: 2.1
Name: powerfit
Version: 0.3.1
Summary: Simple fit functions
Author-email: Tom de Geus <tom@geus.me>
Project-URL: Source, https://github.com/tdegeus/powerfit
Classifier: License :: OSI Approved :: MIT License
Requires-Python: >=3.6
License-File: LICENSE
Requires-Dist: numpy
Requires-Dist: scipy
